[
  {
    "id": 1,
    "text": "Инфляция — это устойчивый рост общего уровня цен.",
    "answer": true,
    "explain": "Инфляция означает устойчивый рост цен и снижение покупательной способности денег.",
    "points": 1
  },
  {
    "id": 2,
    "text": "ВВП — это сумма всех доходов населения.",
    "answer": false,
    "explain": "ВВП — это стоимость конечных товаров и услуг, произведённых за период.",
    "points": 2
  },
  {
    "id": 3,
    "text": "Рост спроса при неизменном предложении обычно повышает цену.",
    "answer": true,
    "explain": "Сдвиг спроса вправо при прежнем предложении ведёт к росту равновесной цены.",
    "points": 1
  },
  {
    "id": 4,
    "text": "Дефляция — это устойчивое снижение общего уровня цен.",
    "answer": true,
    "explain": "Дефляция означает падение цен и может негативно влиять на спрос.",
    "points": 1
  },
  {
    "id": 5,
    "text": "Рост процентных ставок стимулирует инвестиции.",
    "answer": false,
    "explain": "Высокие ставки делают заимствования дороже и снижают инвестиции.",
    "points": 1
  },
  {
    "id": 6,
    "text": "Рыночное равновесие достигается, когда спрос равен предложению.",
    "answer": true,
    "explain": "В точке равновесия отсутствуют дефицит и избыток.",
    "points": 1
  },
  {
    "id": 7,
    "text": "ВВП включает стоимость промежуточных товаров.",
    "answer": false,
    "explain": "ВВП учитывает только конечные товары и услуги.",
    "points": 2
  },
  {
    "id": 8,
    "text": "Безработица фрикционного типа связана с поиском работы.",
    "answer": true,
    "explain": "Фрикционная безработица возникает при смене места работы.",
    "points": 2
  },
  {
    "id": 9,
    "text": "Импорт всегда ухудшает торговый баланс страны.",
    "answer": false,
    "explain": "Импорт может сопровождаться ростом экспорта и выгодой для потребителей.",
    "points": 2
  },
  {
    "id": 10,
    "text": "Эластичность спроса показывает чувствительность спроса к изменению цены.",
    "answer": true,
    "explain": "Эластичность измеряет, как сильно меняется спрос при изменении цены.",
    "points": 2
  },
  {
    "id": 11,
    "text": "Налоги не влияют на поведение производителей.",
    "answer": false,
    "explain": "Налоги увеличивают издержки и влияют на объёмы производства.",
    "points": 2
  },
  {
    "id": 12,
    "text": "Рецессия — это период экономического спада.",
    "answer": true,
    "explain": "Рецессия характеризуется снижением ВВП и занятости.",
    "points": 1
  },
  {
    "id": 13,
    "text": "Субсидии обычно увеличивают предложение товара.",
    "answer": true,
    "explain": "Субсидии снижают издержки производителей.",
    "points": 2
  },
  {
    "id": 14,
    "text": "Монополия — это рынок с большим числом продавцов.",
    "answer": false,
    "explain": "Монополия предполагает одного продавца.",
    "points": 1
  },
  {
    "id": 15,
    "text": "Олигополия характеризуется стратегическим взаимодействием фирм.",
    "answer": true,
    "explain": "Решения одной фирмы влияют на другие.",
    "points": 3
  },
  {
    "id": 16,
    "text": "Центральный банк напрямую устанавливает зарплаты.",
    "answer": false,
    "explain": "ЦБ влияет на экономику через денежно-кредитную политику.",
    "points": 1
  },
  {
    "id": 17,
    "text": "Инфляция снижает реальную покупательную способность денег.",
    "answer": true,
    "explain": "При росте цен на ту же сумму можно купить меньше товаров.",
    "points": 1
  },
  {
    "id": 18,
    "text": "Структурная безработица связана с изменением структуры экономики.",
    "answer": true,
    "explain": "Навыки работников могут не соответствовать новым требованиям рынка.",
    "points": 3
  },
  {
    "id": 19,
    "text": "Повышение налогов всегда увеличивает налоговые поступления.",
    "answer": false,
    "explain": "Существует эффект кривой Лаффера.",
    "points": 4
  },
  {
    "id": 20,
    "text": "Совершенная конкуренция предполагает отсутствие рыночной власти у фирм.",
    "answer": true,
    "explain": "Фирмы являются ценополучателями.",
    "points": 3
  },
  {
    "id": 21,
    "text": "Минимальная заработная плата может привести к безработице.",
    "answer": true,
    "explain": "Если она выше равновесной, спрос на труд снижается.",
    "points": 3
  },
  {
    "id": 22,
    "text": "Денежная масса не влияет на уровень цен в долгосрочном периоде.",
    "answer": false,
    "explain": "В долгосрочном периоде рост денег ведёт к инфляции.",
    "points": 4
  },
  {
    "id": 23,
    "text": "Экспорт увеличивает совокупный спрос.",
    "answer": true,
    "explain": "Экспорт является компонентом совокупного спроса.",
    "points": 2
  },
  {
    "id": 24,
    "text": "Альтернативная стоимость — это стоимость упущенной выгоды.",
    "answer": true,
    "explain": "Она отражает ценность лучшей из нереализованных альтернатив.",
    "points": 3
  },
  {
    "id": 25,
    "text": "Положительная внешняя эффектность приводит к перепроизводству.",
    "answer": false,
    "explain": "Положительные внешние эффекты ведут к недопроизводству.",
    "points": 4
  },
  {
    "id": 26,
    "text": "Отрицательные внешние эффекты оправдывают государственное вмешательство.",
    "answer": true,
    "explain": "Государство может вводить налоги или регулирование.",
    "points": 3
  },
  {
    "id": 27,
    "text": "Инфляция спроса возникает при росте совокупного спроса.",
    "answer": true,
    "explain": "Спрос превышает производственные возможности экономики.",
    "points": 3
  },
  {
    "id": 28,
    "text": "Инфляция издержек связана с ростом затрат производства.",
    "answer": true,
    "explain": "Рост цен на ресурсы увеличивает себестоимость.",
    "points": 3
  },
  {
    "id": 29,
    "text": "Фискальная политика осуществляется центральным банком.",
    "answer": false,
    "explain": "Фискальная политика — это налоги и госрасходы правительства.",
    "points": 2
  },
  {
    "id": 30,
    "text": "Дефицит бюджета может стимулировать экономику в краткосрочном периоде.",
    "answer": true,
    "explain": "Рост госрасходов увеличивает совокупный спрос.",
    "points": 4
  },
  {
    "id": 31,
    "text": "Госдолг всегда вреден для экономики.",
    "answer": false,
    "explain": "Умеренный долг может быть инструментом стабилизации.",
    "points": 4
  },
  {
    "id": 32,
    "text": "Предельная полезность убывает по мере роста потребления.",
    "answer": true,
    "explain": "Каждая дополнительная единица приносит меньшую полезность.",
    "points": 3
  },
  {
    "id": 33,
    "text": "Закон спроса утверждает, что при росте цены спрос растёт.",
    "answer": false,
    "explain": "Закон спроса описывает обратную зависимость.",
    "points": 1
  },
  {
    "id": 34,
    "text": "Ценовой потолок ниже равновесия приводит к дефициту.",
    "answer": true,
    "explain": "Спрос превышает предложение.",
    "points": 3
  },
  {
    "id": 35,
    "text": "Совокупное предложение в долгосрочном периоде вертикально.",
    "answer": true,
    "explain": "Выпуск определяется ресурсами и технологиями.",
    "points": 5
  },
  {
    "id": 36,
    "text": "Экономический рост всегда сопровождается инфляцией.",
    "answer": false,
    "explain": "Рост может происходить без инфляционного давления.",
    "points": 3
  },
  {
    "id": 37,
    "text": "Производительность труда влияет на уровень жизни.",
    "answer": true,
    "explain": "Рост производительности повышает реальные доходы.",
    "points": 2
  },
  {
    "id": 38,
    "text": "Номинальный ВВП учитывает инфляцию.",
    "answer": false,
    "explain": "Инфляцию учитывает реальный ВВП.",
    "points": 2
  },
  {
    "id": 39,
    "text": "Кривая Филлипса описывает связь между инфляцией и безработицей.",
    "answer": true,
    "explain": "В краткосрочном периоде существует компромисс.",
    "points": 4
  },
  {
    "id": 40,
    "text": "Долгосрочно экономика может иметь нулевую безработицу.",
    "answer": false,
    "explain": "Всегда существует естественный уровень безработицы.",
    "points": 4
  },
  {
    "id": 41,
    "text": "Рациональные ожидания могут снизить эффективность экономической политики.",
    "answer": true,
    "explain": "Агенты заранее учитывают действия государства.",
    "points": 5
  },
  {
    "id": 42,
    "text": "Абсолютное преимущество объясняет международную торговлю лучше, чем сравнительное.",
    "answer": false,
    "explain": "Теория сравнительных преимуществ более универсальна.",
    "points": 4
  },
  {
    "id": 43,
    "text": "Сравнительное преимущество основано на альтернативных издержках.",
    "answer": true,
    "explain": "Страны специализируются на товарах с меньшими альтернативными издержками.",
    "points": 5
  },
  {
    "id": 44,
    "text": "Протекционизм всегда повышает благосостояние потребителей.",
    "answer": false,
    "explain": "Торговые барьеры часто приводят к росту цен.",
    "points": 3
  },
  {
    "id": 45,
    "text": "Экстерналии возникают, когда рыночная цена отражает все издержки.",
    "answer": false,
    "explain": "Экстерналии возникают, когда часть издержек не учитывается рынком.",
    "points": 4
  },
  {
    "id": 46,
    "text": "Общественные блага характеризуются неисключаемостью.",
    "answer": true,
    "explain": "Никого нельзя исключить из потребления.",
    "points": 4
  },
  {
    "id": 47,
    "text": "Частные блага являются неконкурентными.",
    "answer": false,
    "explain": "Частные блага конкурентны и исключаемы.",
    "points": 2
  },
  {
    "id": 48,
    "text": "Экономические агенты всегда действуют рационально.",
    "answer": false,
    "explain": "Поведенческая экономика показывает систематические отклонения.",
    "points": 3
  },
  {
    "id": 49,
    "text": "Институциональные факторы влияют на экономический рост.",
    "answer": true,
    "explain": "Качество институтов важно для развития экономики.",
    "points": 4
  },
  {
    "id": 50,
    "text": "Экономика изучает только денежные отношения.",
    "answer": false,
    "explain": "Экономика изучает выбор при ограниченных ресурсах.",
    "points": 1
  },
  {
    "id": 51,
    "text": "Рост человеческого капитала способствует долгосрочному росту.",
    "answer": true,
    "explain": "Образование и навыки повышают производительность.",
    "points": 3
  },
  {
    "id": 52,
    "text": "Совокупный спрос не зависит от уровня цен.",
    "answer": false,
    "explain": "Между уровнем цен и совокупным спросом существует обратная связь.",
    "points": 4
  },
  {
    "id": 53,
    "text": "Монетарная политика эффективнее фискальной в любом периоде.",
    "answer": false,
    "explain": "Эффективность зависит от ситуации и временного горизонта.",
    "points": 5
  }
]
